automl/cli.py
automl/api/app.py
automl/api/schemas.py
automl/core/config.py
automl/core/meta_env.py
automl/core/meta_learner.py
automl/core/quantization.py
automl/data/augmentation.py
automl/data/cleaning.py
automl/hyperparameters/bayesian_opt.py
automl/hyperparameters/evolutionary.py
automl_self_improvement-1.0.1.dist-info/METADATA
automl_self_improvement-1.0.1.dist-info/WHEEL
automl_self_improvement-1.0.1.dist-info/entry_points.txt
automl_self_improvement-1.0.1.dist-info/top_level.txt
automl_self_improvement-1.0.1.dist-info/RECORD
