Metadata-Version: 2.4
Name: automl_self_improvement
Version: 1.0.1
Summary: Autonomous AI model optimization framework with meta-learning and hybrid tuning
Author-email: Krishna Bajpai <krishna@krishnabajpai.me>
License-Expression: MIT
Project-URL: Homepage, https://github.com/krish567366/automl-self-improvement
Project-URL: Documentation, https://github.com/krish567366/automl_self_improvement/tree/main/docs
Project-URL: Repository, https://github.com/krish567366/automl-self-improvement
Project-URL: Consulting, https://krishnabajpai.me
Classifier: Development Status :: 4 - Beta
Classifier: Intended Audience :: Science/Research
Classifier: Topic :: Scientific/Engineering :: Artificial Intelligence
Classifier: Programming Language :: Python :: 3.10
Classifier: Programming Language :: Python :: 3.11
Requires-Dist: torch>=2.0.0
Requires-Dist: optuna>=3.2.0
Requires-Dist: fastapi>=0.95.0
Requires-Dist: stable-baselines3>=2.0.0
Requires-Dist: diffusers>=0.16.0
Requires-Dist: pymoo>=0.6.0
Requires-Dist: scikit-learn>=1.2.0
Requires-Dist: ray[tune]>=2.5.0
Requires-Dist: python-jose>=3.3.0
Requires-Dist: uvicorn>=0.21.0
